{
    "model_name": "hyper",
    "method": "faceid",
    "pipe_kwargs": {
        "num_inference_steps": 4,
        "guidance_scale_a": 1.0,
        "guidance_scale_b": 1.0,
        "width": 1024,
        "height": 1024,
        "dcg_kwargs": {
            "dcg_type": 4,
            "term_preproc": "",
            "term_postproc": "rescale",
            "rescale": 0.75,
            "a_scheduler": "custom",
            "b_scheduler": "custom",
            "sch_kwargs": {
                "custom": {
                    "a": [1.5, 1.5, 1.0, 0.5],
                    "b": [0.5, 1.2, 1.5, 0.3]
                }
            },
            "return_norms": false
        }
    },
    "ip_adapter_scale": 0.8,
    "faceid_lora_scale": 1.0,
    "reset_gs_to_default": false,
    "patch_pipe": true,
    "am_patch_kwargs": {
        "target_parts": ["down", "up"],
        "target_tokens": [0, 1, 2, 3],
        "target_tsteps": [0, 1],
        "am_transforms": ["pow", "scale"],
        "inverse_neg_transforms": false,
        "apply_schedule": false,
        "apply_adain": false
    }
}
